pydevf/__init__.py
pydevf/__main__.py
pydevf/_pydevf.py
pydevf/pydev_formatter.jar
pydevf/version.py
pydevf/pydev_formatter_lib/org.eclipse.equinox.common_3.10.0.v20180412-1130.jar
pydevf/pydev_formatter_lib/org.eclipse.text_3.6.300.v20180430-1330.jar
pydevf-0.1.5.dist-info/METADATA
pydevf-0.1.5.dist-info/RECORD
pydevf-0.1.5.dist-info/WHEEL
pydevf-0.1.5.dist-info/entry_points.txt
pydevf-0.1.5.dist-info/top_level.txt
