Metadata-Version: 1.1
Name: pydevf
Version: 0.1.5
Summary: PyDev Code Formatter
Home-page: https://github.com/fabioz/pydevf
Author: Fabio Zadrozny
Author-email: fabiofz@gmail.com
License: EPL (Eclipse Public License)
Keywords: pydevf,pydev formatter,pydev
Platform: UNKNOWN
Classifier: Development Status :: 4 - Beta
Classifier: Intended Audience :: Developers
Classifier: License :: OSI Approved :: Eclipse Public License 2.0 (EPL-2.0)
Classifier: Natural Language :: English
Classifier: Programming Language :: Python :: 2
Classifier: Programming Language :: Python :: 2.7
Classifier: Programming Language :: Python :: 3
Classifier: Programming Language :: Python :: 3.4
Classifier: Programming Language :: Python :: 3.5
Classifier: Programming Language :: Python :: 3.6
